{"def": [{"memberName": "AlignmentGift", "packageName": "com.ankamagames.dofus.datacenter.alignments", "fields": [{"name": "id", "type": -1}, {"name": "nameId", "type": -5}, {"name": "effectId", "type": -1}, {"name": "gfxId", "type": -1}]}], "data": [{"id": 1, "nameId": 67, "effectId": 10, "gfxId": 1}, {"id": 2, "nameId": 66, "effectId": 2, "gfxId": 2}, {"id": 3, "nameId": 87, "effectId": 17, "gfxId": 3}, {"id": 4, "nameId": 81, "effectId": 18, "gfxId": 4}, {"id": 5, "nameId": 78, "effectId": 19, "gfxId": 5}, {"id": 6, "nameId": 85, "effectId": 20, "gfxId": 6}, {"id": 7, "nameId": 75, "effectId": 21, "gfxId": 7}, {"id": 8, "nameId": 76, "effectId": 4, "gfxId": 8}, {"id": 9, "nameId": 68, "effectId": 22, "gfxId": 9}, {"id": 10, "nameId": 77, "effectId": -1, "gfxId": 10}, {"id": 11, "nameId": 70, "effectId": -1, "gfxId": 11}, {"id": 12, "nameId": 80, "effectId": -1, "gfxId": 12}, {"id": 13, "nameId": 79, "effectId": 23, "gfxId": 12}, {"id": 15, "nameId": 86, "effectId": 29, "gfxId": 3}, {"id": 16, "nameId": 72, "effectId": 31, "gfxId": 5}, {"id": 17, "nameId": 82, "effectId": 32, "gfxId": 6}, {"id": 18, "nameId": 84, "effectId": 33, "gfxId": 7}, {"id": 19, "nameId": 83, "effectId": 30, "gfxId": 4}, {"id": 20, "nameId": 74, "effectId": 40, "gfxId": 13}, {"id": 21, "nameId": 69, "effectId": -1, "gfxId": 1}, {"id": 22, "nameId": 73, "effectId": 23, "gfxId": 12}, {"id": 23, "nameId": 71, "effectId": -1, "gfxId": 11}, {"id": 24, "nameId": 806702, "effectId": 4, "gfxId": 1}, {"id": 25, "nameId": 806703, "effectId": 8, "gfxId": 1}, {"id": 26, "nameId": 806704, "effectId": 9, "gfxId": 1}, {"id": 27, "nameId": 806705, "effectId": 7, "gfxId": 1}, {"id": 28, "nameId": 806706, "effectId": 6, "gfxId": 1}, {"id": 29, "nameId": 806709, "effectId": 1, "gfxId": 1}, {"id": 30, "nameId": 806710, "effectId": 41, "gfxId": 1}, {"id": 31, "nameId": 806711, "effectId": 42, "gfxId": 1}, {"id": 32, "nameId": 806712, "effectId": 14, "gfxId": 0}, {"id": 33, "nameId": 806713, "effectId": 15, "gfxId": 0}, {"id": 34, "nameId": 806714, "effectId": 39, "gfxId": 1}, {"id": 35, "nameId": 806715, "effectId": 43, "gfxId": 1}, {"id": 36, "nameId": 806716, "effectId": 44, "gfxId": 1}, {"id": 37, "nameId": 806717, "effectId": 2, "gfxId": 1}, {"id": 38, "nameId": 806718, "effectId": 40, "gfxId": 1}, {"id": 39, "nameId": 806719, "effectId": 45, "gfxId": 1}, {"id": 40, "nameId": 806720, "effectId": 46, "gfxId": 1}, {"id": 41, "nameId": 806721, "effectId": 47, "gfxId": 1}, {"id": 42, "nameId": 806722, "effectId": 48, "gfxId": 1}, {"id": 43, "nameId": 806723, "effectId": 49, "gfxId": 1}, {"id": 44, "nameId": 806724, "effectId": 50, "gfxId": 1}, {"id": 45, "nameId": 806725, "effectId": 51, "gfxId": 1}, {"id": 46, "nameId": 806726, "effectId": 52, "gfxId": 1}, {"id": 47, "nameId": 806727, "effectId": 53, "gfxId": 1}, {"id": 48, "nameId": 806728, "effectId": 54, "gfxId": 1}, {"id": 49, "nameId": 806729, "effectId": 55, "gfxId": 1}, {"id": 50, "nameId": 806730, "effectId": 27, "gfxId": 1}, {"id": 51, "nameId": 806731, "effectId": 26, "gfxId": 1}, {"id": 52, "nameId": 806732, "effectId": 25, "gfxId": 1}, {"id": 53, "nameId": 806733, "effectId": 24, "gfxId": 1}, {"id": 54, "nameId": 806734, "effectId": 56, "gfxId": 1}, {"id": 55, "nameId": 806735, "effectId": 57, "gfxId": 1}, {"id": 56, "nameId": 806736, "effectId": 58, "gfxId": 1}, {"id": 57, "nameId": 806737, "effectId": 59, "gfxId": 1}, {"id": 58, "nameId": 806740, "effectId": 22, "gfxId": 1}, {"id": 59, "nameId": 806741, "effectId": 60, "gfxId": 1}, {"id": 60, "nameId": 807448, "effectId": 8, "gfxId": 1}, {"id": 61, "nameId": 807449, "effectId": 4, "gfxId": 1}, {"id": 62, "nameId": 807450, "effectId": 43, "gfxId": 1}, {"id": 63, "nameId": 807451, "effectId": 39, "gfxId": 1}, {"id": 64, "nameId": 807452, "effectId": 17, "gfxId": 3}, {"id": 65, "nameId": 807453, "effectId": 19, "gfxId": 5}, {"id": 66, "nameId": 807454, "effectId": 20, "gfxId": 6}, {"id": 67, "nameId": 807455, "effectId": 24, "gfxId": 1}, {"id": 68, "nameId": 807456, "effectId": 57, "gfxId": 1}, {"id": 69, "nameId": 807457, "effectId": 59, "gfxId": 1}, {"id": 70, "nameId": 807458, "effectId": 25, "gfxId": 1}, {"id": 71, "nameId": 807459, "effectId": 26, "gfxId": 1}, {"id": 72, "nameId": 807460, "effectId": 58, "gfxId": 1}, {"id": 73, "nameId": 807461, "effectId": 56, "gfxId": 1}, {"id": 74, "nameId": 807462, "effectId": 29, "gfxId": 3}, {"id": 75, "nameId": 807463, "effectId": 33, "gfxId": 7}, {"id": 76, "nameId": 807464, "effectId": 30, "gfxId": 4}, {"id": 77, "nameId": 807465, "effectId": 31, "gfxId": 5}, {"id": 78, "nameId": 807466, "effectId": 4, "gfxId": 1}, {"id": 79, "nameId": 807467, "effectId": 32, "gfxId": 6}, {"id": 80, "nameId": 807468, "effectId": 21, "gfxId": 7}, {"id": 81, "nameId": 807469, "effectId": 18, "gfxId": 4}, {"id": 82, "nameId": 807470, "effectId": 27, "gfxId": 1}, {"id": 83, "nameId": 807471, "effectId": 43, "gfxId": 1}, {"id": 84, "nameId": 807472, "effectId": 39, "gfxId": 1}, {"id": 85, "nameId": 807473, "effectId": 4, "gfxId": 8}, {"id": 86, "nameId": 807474, "effectId": 42, "gfxId": 1}, {"id": 87, "nameId": 807475, "effectId": 17, "gfxId": 3}, {"id": 88, "nameId": 807476, "effectId": 41, "gfxId": 1}, {"id": 89, "nameId": 807477, "effectId": 40, "gfxId": 1}, {"id": 90, "nameId": 807478, "effectId": 40, "gfxId": 13}, {"id": 91, "nameId": 807479, "effectId": 19, "gfxId": 5}, {"id": 92, "nameId": 807480, "effectId": 1, "gfxId": 1}, {"id": 93, "nameId": 807481, "effectId": 60, "gfxId": 1}, {"id": 94, "nameId": 807482, "effectId": 20, "gfxId": 6}, {"id": 95, "nameId": 807483, "effectId": 23, "gfxId": 12}, {"id": 96, "nameId": 807484, "effectId": 22, "gfxId": 1}, {"id": 97, "nameId": 807485, "effectId": 24, "gfxId": 1}, {"id": 98, "nameId": 807486, "effectId": 45, "gfxId": 1}, {"id": 99, "nameId": 807487, "effectId": 6, "gfxId": 1}, {"id": 100, "nameId": 807488, "effectId": 57, "gfxId": 1}, {"id": 101, "nameId": 807489, "effectId": 59, "gfxId": 1}, {"id": 102, "nameId": 807490, "effectId": 2, "gfxId": 1}, {"id": 103, "nameId": 807491, "effectId": 2, "gfxId": 2}, {"id": 104, "nameId": 807492, "effectId": 25, "gfxId": 1}, {"id": 105, "nameId": 807493, "effectId": -1, "gfxId": 1}, {"id": 106, "nameId": 807494, "effectId": 44, "gfxId": 1}, {"id": 107, "nameId": 807495, "effectId": 26, "gfxId": 1}, {"id": 108, "nameId": 807496, "effectId": 7, "gfxId": 1}, {"id": 109, "nameId": 807497, "effectId": 58, "gfxId": 1}, {"id": 110, "nameId": 807498, "effectId": -1, "gfxId": 12}, {"id": 111, "nameId": 807499, "effectId": 56, "gfxId": 1}, {"id": 112, "nameId": 807500, "effectId": 15, "gfxId": 0}, {"id": 113, "nameId": 807501, "effectId": 29, "gfxId": 3}, {"id": 114, "nameId": 807502, "effectId": 14, "gfxId": 0}, {"id": 115, "nameId": 807503, "effectId": 22, "gfxId": 9}, {"id": 116, "nameId": 807504, "effectId": 33, "gfxId": 7}, {"id": 117, "nameId": 807505, "effectId": 10, "gfxId": 1}, {"id": 118, "nameId": 807506, "effectId": 49, "gfxId": 1}, {"id": 119, "nameId": 807507, "effectId": 30, "gfxId": 4}, {"id": 120, "nameId": 807508, "effectId": 54, "gfxId": 1}, {"id": 121, "nameId": 807509, "effectId": 51, "gfxId": 1}, {"id": 122, "nameId": 807510, "effectId": 31, "gfxId": 5}, {"id": 123, "nameId": 807511, "effectId": 53, "gfxId": 1}, {"id": 124, "nameId": 807512, "effectId": 48, "gfxId": 1}, {"id": 125, "nameId": 807513, "effectId": 32, "gfxId": 6}, {"id": 126, "nameId": 807514, "effectId": 47, "gfxId": 1}, {"id": 127, "nameId": 807515, "effectId": 52, "gfxId": 1}, {"id": 128, "nameId": 807516, "effectId": 21, "gfxId": 7}, {"id": 129, "nameId": 807517, "effectId": 50, "gfxId": 1}, {"id": 130, "nameId": 807518, "effectId": 18, "gfxId": 4}, {"id": 131, "nameId": 807519, "effectId": 55, "gfxId": 1}, {"id": 132, "nameId": 807520, "effectId": 46, "gfxId": 1}, {"id": 133, "nameId": 807521, "effectId": 27, "gfxId": 1}, {"id": 134, "nameId": 807522, "effectId": -1, "gfxId": 11}, {"id": 135, "nameId": 807523, "effectId": 4, "gfxId": 8}, {"id": 136, "nameId": 807524, "effectId": -1, "gfxId": 11}, {"id": 137, "nameId": 807525, "effectId": 9, "gfxId": 1}, {"id": 138, "nameId": 807526, "effectId": 42, "gfxId": 1}, {"id": 139, "nameId": 807527, "effectId": -1, "gfxId": 10}, {"id": 140, "nameId": 807528, "effectId": 41, "gfxId": 1}, {"id": 142, "nameId": 807530, "effectId": 23, "gfxId": 12}, {"id": 143, "nameId": 807531, "effectId": 40, "gfxId": 1}, {"id": 144, "nameId": 807532, "effectId": 40, "gfxId": 13}, {"id": 145, "nameId": 807533, "effectId": 1, "gfxId": 1}, {"id": 146, "nameId": 807534, "effectId": 60, "gfxId": 1}, {"id": 147, "nameId": 807535, "effectId": 23, "gfxId": 12}, {"id": 148, "nameId": 807536, "effectId": 22, "gfxId": 1}, {"id": 149, "nameId": 807537, "effectId": 45, "gfxId": 1}, {"id": 150, "nameId": 807538, "effectId": 6, "gfxId": 1}, {"id": 151, "nameId": 807539, "effectId": 2, "gfxId": 1}, {"id": 152, "nameId": 807540, "effectId": 2, "gfxId": 2}, {"id": 153, "nameId": 807541, "effectId": -1, "gfxId": 1}, {"id": 154, "nameId": 807542, "effectId": 44, "gfxId": 1}, {"id": 155, "nameId": 807543, "effectId": 7, "gfxId": 1}, {"id": 156, "nameId": 807544, "effectId": -1, "gfxId": 12}, {"id": 157, "nameId": 807545, "effectId": 4, "gfxId": 1}, {"id": 158, "nameId": 807546, "effectId": 15, "gfxId": 0}, {"id": 159, "nameId": 807547, "effectId": 14, "gfxId": 0}, {"id": 160, "nameId": 807548, "effectId": 43, "gfxId": 1}, {"id": 161, "nameId": 807549, "effectId": 39, "gfxId": 1}, {"id": 162, "nameId": 807550, "effectId": 22, "gfxId": 9}, {"id": 163, "nameId": 807551, "effectId": 17, "gfxId": 3}, {"id": 164, "nameId": 807552, "effectId": 10, "gfxId": 1}, {"id": 165, "nameId": 807553, "effectId": 19, "gfxId": 5}, {"id": 166, "nameId": 807554, "effectId": 20, "gfxId": 6}, {"id": 167, "nameId": 807555, "effectId": 49, "gfxId": 1}, {"id": 168, "nameId": 807556, "effectId": 24, "gfxId": 1}, {"id": 169, "nameId": 807557, "effectId": 54, "gfxId": 1}, {"id": 170, "nameId": 807558, "effectId": 57, "gfxId": 1}, {"id": 171, "nameId": 807559, "effectId": 59, "gfxId": 1}, {"id": 172, "nameId": 807560, "effectId": 51, "gfxId": 1}, {"id": 173, "nameId": 807561, "effectId": 25, "gfxId": 1}, {"id": 174, "nameId": 807682, "effectId": 53, "gfxId": 1}, {"id": 175, "nameId": 807563, "effectId": 26, "gfxId": 1}, {"id": 176, "nameId": 807564, "effectId": 58, "gfxId": 1}, {"id": 177, "nameId": 807565, "effectId": 48, "gfxId": 1}, {"id": 178, "nameId": 807566, "effectId": 56, "gfxId": 1}, {"id": 179, "nameId": 807567, "effectId": 29, "gfxId": 3}, {"id": 180, "nameId": 807568, "effectId": 47, "gfxId": 1}, {"id": 181, "nameId": 807569, "effectId": 33, "gfxId": 7}, {"id": 182, "nameId": 807570, "effectId": 52, "gfxId": 1}, {"id": 183, "nameId": 807571, "effectId": 30, "gfxId": 4}, {"id": 184, "nameId": 807572, "effectId": 50, "gfxId": 1}, {"id": 185, "nameId": 807573, "effectId": 31, "gfxId": 5}, {"id": 186, "nameId": 807576, "effectId": 55, "gfxId": 1}, {"id": 187, "nameId": 807575, "effectId": 32, "gfxId": 6}, {"id": 188, "nameId": 807577, "effectId": 21, "gfxId": 7}, {"id": 189, "nameId": 807578, "effectId": 46, "gfxId": 1}, {"id": 190, "nameId": 807579, "effectId": 18, "gfxId": 4}, {"id": 191, "nameId": 807580, "effectId": -1, "gfxId": 11}, {"id": 192, "nameId": 807581, "effectId": 27, "gfxId": 1}, {"id": 193, "nameId": 807582, "effectId": 4, "gfxId": 8}, {"id": 194, "nameId": 807583, "effectId": -1, "gfxId": 11}, {"id": 195, "nameId": 807584, "effectId": 42, "gfxId": 1}, {"id": 196, "nameId": 807585, "effectId": 9, "gfxId": 1}, {"id": 197, "nameId": 807586, "effectId": 41, "gfxId": 1}, {"id": 198, "nameId": 807587, "effectId": -1, "gfxId": 10}, {"id": 199, "nameId": 807588, "effectId": 40, "gfxId": 1}, {"id": 200, "nameId": 807589, "effectId": 40, "gfxId": 13}, {"id": 201, "nameId": 807590, "effectId": 1, "gfxId": 1}, {"id": 202, "nameId": 807591, "effectId": 60, "gfxId": 1}, {"id": 203, "nameId": 807592, "effectId": 23, "gfxId": 12}, {"id": 204, "nameId": 807593, "effectId": 8, "gfxId": 1}, {"id": 205, "nameId": 807594, "effectId": 22, "gfxId": 1}, {"id": 206, "nameId": 807595, "effectId": 45, "gfxId": 1}, {"id": 207, "nameId": 807596, "effectId": 23, "gfxId": 12}, {"id": 208, "nameId": 807597, "effectId": 6, "gfxId": 1}, {"id": 209, "nameId": 807598, "effectId": 2, "gfxId": 1}, {"id": 210, "nameId": 807599, "effectId": 2, "gfxId": 2}, {"id": 211, "nameId": 807600, "effectId": -1, "gfxId": 1}, {"id": 212, "nameId": 807601, "effectId": 44, "gfxId": 1}, {"id": 213, "nameId": 807602, "effectId": 7, "gfxId": 1}, {"id": 214, "nameId": 807603, "effectId": -1, "gfxId": 12}, {"id": 215, "nameId": 807604, "effectId": 15, "gfxId": 0}, {"id": 216, "nameId": 807605, "effectId": 14, "gfxId": 0}, {"id": 217, "nameId": 807606, "effectId": 22, "gfxId": 9}, {"id": 218, "nameId": 807607, "effectId": 10, "gfxId": 1}, {"id": 219, "nameId": 807608, "effectId": 4, "gfxId": 1}, {"id": 220, "nameId": 807609, "effectId": 49, "gfxId": 1}, {"id": 221, "nameId": 807610, "effectId": 43, "gfxId": 1}, {"id": 222, "nameId": 807611, "effectId": 54, "gfxId": 1}, {"id": 223, "nameId": 807612, "effectId": 51, "gfxId": 1}, {"id": 224, "nameId": 807613, "effectId": 39, "gfxId": 1}, {"id": 225, "nameId": 807614, "effectId": 53, "gfxId": 1}, {"id": 226, "nameId": 807615, "effectId": 17, "gfxId": 3}, {"id": 227, "nameId": 807616, "effectId": 48, "gfxId": 1}, {"id": 228, "nameId": 807617, "effectId": 47, "gfxId": 1}, {"id": 229, "nameId": 807618, "effectId": 19, "gfxId": 5}, {"id": 230, "nameId": 807619, "effectId": 52, "gfxId": 1}, {"id": 231, "nameId": 807620, "effectId": 20, "gfxId": 6}, {"id": 232, "nameId": 807621, "effectId": 50, "gfxId": 1}, {"id": 233, "nameId": 807622, "effectId": 24, "gfxId": 1}, {"id": 234, "nameId": 807623, "effectId": 55, "gfxId": 1}, {"id": 235, "nameId": 807624, "effectId": 57, "gfxId": 1}, {"id": 236, "nameId": 807625, "effectId": 46, "gfxId": 1}, {"id": 237, "nameId": 807626, "effectId": 59, "gfxId": 1}, {"id": 238, "nameId": 807627, "effectId": -1, "gfxId": 11}, {"id": 239, "nameId": 807628, "effectId": 25, "gfxId": 1}, {"id": 240, "nameId": 807629, "effectId": -1, "gfxId": 11}, {"id": 241, "nameId": 807630, "effectId": 9, "gfxId": 1}, {"id": 242, "nameId": 807631, "effectId": 26, "gfxId": 1}, {"id": 243, "nameId": 807632, "effectId": -1, "gfxId": 10}, {"id": 244, "nameId": 807633, "effectId": 8, "gfxId": 1}, {"id": 245, "nameId": 807634, "effectId": 58, "gfxId": 1}, {"id": 246, "nameId": 807635, "effectId": 23, "gfxId": 12}, {"id": 247, "nameId": 807636, "effectId": 56, "gfxId": 1}, {"id": 248, "nameId": 807637, "effectId": 29, "gfxId": 3}, {"id": 249, "nameId": 807638, "effectId": 33, "gfxId": 7}, {"id": 250, "nameId": 807639, "effectId": 30, "gfxId": 4}, {"id": 251, "nameId": 807640, "effectId": 31, "gfxId": 5}, {"id": 252, "nameId": 807641, "effectId": 32, "gfxId": 6}, {"id": 253, "nameId": 807642, "effectId": 21, "gfxId": 7}, {"id": 254, "nameId": 807643, "effectId": 18, "gfxId": 4}, {"id": 255, "nameId": 807644, "effectId": 27, "gfxId": 1}, {"id": 256, "nameId": 807645, "effectId": 4, "gfxId": 8}, {"id": 257, "nameId": 807646, "effectId": 42, "gfxId": 1}, {"id": 258, "nameId": 807647, "effectId": 41, "gfxId": 1}, {"id": 259, "nameId": 807648, "effectId": 40, "gfxId": 1}, {"id": 260, "nameId": 807649, "effectId": 40, "gfxId": 13}, {"id": 261, "nameId": 807650, "effectId": 1, "gfxId": 1}, {"id": 262, "nameId": 807651, "effectId": 60, "gfxId": 1}, {"id": 263, "nameId": 807652, "effectId": 23, "gfxId": 12}, {"id": 264, "nameId": 807653, "effectId": 22, "gfxId": 1}, {"id": 265, "nameId": 807654, "effectId": 45, "gfxId": 1}, {"id": 266, "nameId": 807655, "effectId": 6, "gfxId": 1}, {"id": 267, "nameId": 807656, "effectId": 2, "gfxId": 1}, {"id": 268, "nameId": 807657, "effectId": 2, "gfxId": 2}, {"id": 269, "nameId": 807658, "effectId": -1, "gfxId": 1}, {"id": 270, "nameId": 807659, "effectId": 44, "gfxId": 1}, {"id": 271, "nameId": 807660, "effectId": 7, "gfxId": 1}, {"id": 272, "nameId": 807661, "effectId": -1, "gfxId": 12}, {"id": 273, "nameId": 807662, "effectId": 15, "gfxId": 0}, {"id": 274, "nameId": 807663, "effectId": 14, "gfxId": 0}, {"id": 275, "nameId": 807664, "effectId": 22, "gfxId": 9}, {"id": 276, "nameId": 807665, "effectId": 10, "gfxId": 1}, {"id": 277, "nameId": 807666, "effectId": 49, "gfxId": 1}, {"id": 278, "nameId": 807667, "effectId": 54, "gfxId": 1}, {"id": 279, "nameId": 807668, "effectId": 51, "gfxId": 1}, {"id": 280, "nameId": 807669, "effectId": 53, "gfxId": 1}, {"id": 281, "nameId": 807670, "effectId": 48, "gfxId": 1}, {"id": 282, "nameId": 807671, "effectId": 47, "gfxId": 1}, {"id": 283, "nameId": 807672, "effectId": 52, "gfxId": 1}, {"id": 284, "nameId": 807673, "effectId": 50, "gfxId": 1}, {"id": 285, "nameId": 807674, "effectId": 55, "gfxId": 1}, {"id": 286, "nameId": 807675, "effectId": 46, "gfxId": 1}, {"id": 287, "nameId": 807676, "effectId": -1, "gfxId": 11}, {"id": 288, "nameId": 807677, "effectId": -1, "gfxId": 11}, {"id": 289, "nameId": 807678, "effectId": 9, "gfxId": 1}, {"id": 290, "nameId": 807679, "effectId": -1, "gfxId": 10}, {"id": 291, "nameId": 807680, "effectId": 8, "gfxId": 1}, {"id": 292, "nameId": 807681, "effectId": 23, "gfxId": 12}]}