{
	"def": [
		{
			"memberName": "Job",
			"packageName": "com.ankamagames.dofus.datacenter.jobs",
			"fields": [
				{
					"name": "id",
					"type": -1
				},
				{
					"name": "nameId",
					"type": -5
				},
				{
					"name": "iconId",
					"type": -1
				},
				{
					"name": "hasLegendaryCraft",
					"type": -2
				}
			]
		}
	],
	"data": [
		{
			"id": 1,
			"nameId": 2736,
			"iconId": -1,
			"hasLegendaryCraft": false
		},
		{
			"id": 2,
			"nameId": 2706,
			"iconId": 1,
			"hasLegendaryCraft": false
		},
		{
			"id": 11,
			"nameId": 524455,
			"iconId": 10,
			"hasLegendaryCraft": true
		},
		{
			"id": 13,
			"nameId": 523974,
			"iconId": 6,
			"hasLegendaryCraft": true
		},
		{
			"id": 15,
			"nameId": 2752,
			"iconId": 5,
			"hasLegendaryCraft": true
		},
		{
			"id": 16,
			"nameId": 2740,
			"iconId": 15,
			"hasLegendaryCraft": false
		},
		{
			"id": 24,
			"nameId": 2703,
			"iconId": 13,
			"hasLegendaryCraft": false
		},
		{
			"id": 26,
			"nameId": 2770,
			"iconId": 14,
			"hasLegendaryCraft": false
		},
		{
			"id": 27,
			"nameId": 2718,
			"iconId": 20,
			"hasLegendaryCraft": true
		},
		{
			"id": 28,
			"nameId": 2758,
			"iconId": 18,
			"hasLegendaryCraft": false
		},
		{
			"id": 36,
			"nameId": 2785,
			"iconId": 30,
			"hasLegendaryCraft": false
		},
		{
			"id": 41,
			"nameId": 2733,
			"iconId": 32,
			"hasLegendaryCraft": false
		},
		{
			"id": 44,
			"nameId": 523971,
			"iconId": 24,
			"hasLegendaryCraft": false
		},
		{
			"id": 48,
			"nameId": 523973,
			"iconId": 28,
			"hasLegendaryCraft": false
		},
		{
			"id": 60,
			"nameId": 523972,
			"iconId": 40,
			"hasLegendaryCraft": true
		},
		{
			"id": 62,
			"nameId": 2782,
			"iconId": 36,
			"hasLegendaryCraft": false
		},
		{
			"id": 63,
			"nameId": 2779,
			"iconId": 37,
			"hasLegendaryCraft": false
		},
		{
			"id": 64,
			"nameId": 2776,
			"iconId": 35,
			"hasLegendaryCraft": false
		},
		{
			"id": 65,
			"nameId": 2700,
			"iconId": 34,
			"hasLegendaryCraft": false
		},
		{
			"id": 74,
			"nameId": 721512,
			"iconId": 41,
			"hasLegendaryCraft": false
		},
		{
			"id": 75,
			"nameId": 836222,
			"iconId": 42,
			"hasLegendaryCraft": false
		},
		{
			"id": 78,
			"nameId": 951966,
			"iconId": 42,
			"hasLegendaryCraft": false
		}
	]
}